coqpit/__init__.py
coqpit/coqpit.py
coqpit/py.typed
coqpit_config-0.2.3.dist-info/METADATA
coqpit_config-0.2.3.dist-info/WHEEL
coqpit_config-0.2.3.dist-info/licenses/LICENSE.txt
coqpit_config-0.2.3.dist-info/RECORD
