Metadata-Version: 2.4
Name: coqpit-config
Version: 0.2.3
Summary: Simple (maybe too simple), light-weight config management through python data-classes.
Project-URL: Repository, https://github.com/idiap/coqui-ai-coqpit
Project-URL: Issues, https://github.com/idiap/coqui-ai-coqpit/issues
Author-email: Eren Gölge <egolge@coqui.ai>
Maintainer-email: Enno Hermann <enno.hermann@gmail.com>
License: MIT
License-File: LICENSE.txt
Classifier: Development Status :: 4 - Beta
Classifier: Intended Audience :: Developers
Classifier: Operating System :: MacOS
Classifier: Operating System :: Microsoft :: Windows
Classifier: Operating System :: POSIX :: Linux
Classifier: Programming Language :: Python
Classifier: Programming Language :: Python :: 3
Classifier: Programming Language :: Python :: 3.10
Classifier: Programming Language :: Python :: 3.11
Classifier: Programming Language :: Python :: 3.12
Classifier: Programming Language :: Python :: 3.13
Classifier: Programming Language :: Python :: 3.14
Requires-Python: >=3.10
Requires-Dist: typing-extensions>=4.10
